PhyloSuite/NEWS.md
PhyloSuite/PhyloSuite.py
PhyloSuite/PhyloSuite_citation.enw
PhyloSuite/PhyloSuite_citation.ris
PhyloSuite/PhyloSuite_citation.xml
PhyloSuite/__init__.py
PhyloSuite/style.qss
PhyloSuite/manual/Manual.pdf
PhyloSuite/src/CustomWidget.py
PhyloSuite/src/Launcher.py
PhyloSuite/src/Lg_ClipQuery.py
PhyloSuite/src/Lg_Concatenate.py
PhyloSuite/src/Lg_ConvertFmt.py
PhyloSuite/src/Lg_Gblocks.py
PhyloSuite/src/Lg_HmmCleaner.py
PhyloSuite/src/Lg_IQTREE.py
PhyloSuite/src/Lg_ModelFinder.py
PhyloSuite/src/Lg_Mrbayes.py
PhyloSuite/src/Lg_NmlPoPup.py
PhyloSuite/src/Lg_PartitionFinder.py
PhyloSuite/src/Lg_RSCUfig.py
PhyloSuite/src/Lg_SerhNCBI.py
PhyloSuite/src/Lg_addFiles.py
PhyloSuite/src/Lg_compareTable.py
PhyloSuite/src/Lg_displaySettings.py
PhyloSuite/src/Lg_extractSettings.py
PhyloSuite/src/Lg_extracter.py
PhyloSuite/src/Lg_gbEditor.py
PhyloSuite/src/Lg_macse.py
PhyloSuite/src/Lg_mafft.py
PhyloSuite/src/Lg_parseANNT.py
PhyloSuite/src/Lg_seqViewer.py
PhyloSuite/src/Lg_settings.py
PhyloSuite/src/Lg_trimAl.py
PhyloSuite/src/Lg_workflow.py
PhyloSuite/src/__init__.py
PhyloSuite/src/codonusage.py
PhyloSuite/src/factory.py
PhyloSuite/src/findANDreplace.py
PhyloSuite/src/handleGB.py
PhyloSuite/src/main.py
PhyloSuite/src/preset_values.py
PhyloSuite/src/rscuStack.py
PhyloSuite/src/rscuSum.py
PhyloSuite/src/update.py
PhyloSuite/tests/Test_run.pdf
PhyloSuite/tests/marine_turtle_mitogenomes.gb
PhyloSuite/uifiles/Concatenate.ui
PhyloSuite/uifiles/ConvertFmt.ui
PhyloSuite/uifiles/HmmCleaner.ui
PhyloSuite/uifiles/IQ_TREE.ui
PhyloSuite/uifiles/MACSE.ui
PhyloSuite/uifiles/MainWindow.ui
PhyloSuite/uifiles/ModelFinder.ui
PhyloSuite/uifiles/MrBayes.ui
PhyloSuite/uifiles/NCBI.ui
PhyloSuite/uifiles/NmlPoPup.ui
PhyloSuite/uifiles/PF_exe_path.ui
PhyloSuite/uifiles/RSCUfig.ui
PhyloSuite/uifiles/SeqViewer.ui
PhyloSuite/uifiles/Ui_Concatenate.py
PhyloSuite/uifiles/Ui_ConvertFmt.py
PhyloSuite/uifiles/Ui_HmmCleaner.py
PhyloSuite/uifiles/Ui_IQ_TREE.py
PhyloSuite/uifiles/Ui_MACSE.py
PhyloSuite-1.1.16.post1.dist-info/LICENSE
PhyloSuite-1.1.16.post1.dist-info/METADATA
PhyloSuite-1.1.16.post1.dist-info/WHEEL
PhyloSuite-1.1.16.post1.dist-info/entry_points.txt
PhyloSuite-1.1.16.post1.dist-info/top_level.txt
PhyloSuite-1.1.16.post1.dist-info/RECORD
