Metadata-Version: 2.1
Name: PhyloSuite
Version: 1.1.16.post1
Summary: A desktop platform for streamlined molecular sequence data management and state of the art evolutionary phylogenetics studies.
Home-page: https://github.com/dongzhang0725/PhyloSuite
Author: Dong Zhang
Author-email: dongzhang0725@gmail.com
License: GNU Affero General Public License v3 or later (AGPLv3+)
Platform: Linux; MacOS X; Windows
Classifier: License :: OSI Approved :: GNU Affero General Public License v3 or later (AGPLv3+)
Classifier: Programming Language :: Python
Classifier: Programming Language :: Python :: 3
Classifier: Programming Language :: Python :: 3.6
Classifier: Topic :: Software Development :: User Interfaces
Requires-Python: >=3.6.0
Requires-Dist: biopython
Requires-Dist: python-dateutil
Requires-Dist: suds-py3
Requires-Dist: PyQt5 (==5.10.1)
Requires-Dist: reportlab
Requires-Dist: psutil
Requires-Dist: pywin32 ; platform_system == "Windows"
